{
  "errorCode": 0,
  "msg": "Success.",
  "result": {
    "totalRows": 19,
    "currentPage": 1,
    "currentSize": 100,
    "data": [
      {
        "mac": "F2-36-40-FD-80-F5",
        "name": "Pixel-8-Pro",
        "hostName": "Pixel-8-Pro",
        "deviceType": "unknown",
        "ip": "192.168.10.102",
        "ipv6List": [],
        "connectType": 1,
        "connectDevType": "ap",
        "connectedToWirelessRouter": false,
        "wireless": true,
        "ssid": "GalCaf",
        "signalLevel": 70,
        "healthScore": -1,
        "signalRank": 4,
        "wifiMode": 5,
        "apName": "Galeron AP",
        "apMac": "98-25-4A-41-5D-C2",
        "radioId": 1,
        "channel": 36,
        "rxRate": 585000,
        "txRate": 526000,
        "powerSave": true,
        "rssi": -62,
        "snr": 33,
        "vid": 0,
        "dot1xIdentity": "",
        "activity": 0,
        "trafficDown": 17864798,
        "trafficUp": 3329251,
        "uptime": 5554,
        "lastSeen": 1719770002776,
        "authStatus": 0,
        "guest": false,
        "active": true,
        "manager": false,
        "downPacket": 17685,
        "upPacket": 12034,
        "support5g2": false,
        "multiLink": []
      },
      {
        "mac": "BC-51-FE-28-21-8D",
        "name": "Camaras Galeron",
        "hostName": "--",
        "deviceType": "unknown",
        "ip": "192.168.10.12",
        "connectType": 2,
        "connectDevType": "gateway",
        "connectedToWirelessRouter": false,
        "wireless": false,
        "healthScore": -1,
        "gatewayMac": "98-25-4A-63-B5-1E",
        "gatewayName": "Gateway",
        "vid": 1,
        "networkName": "Default LAN",
        "activity": 21,
        "trafficDown": 60831,
        "trafficUp": 174729,
        "uptime": 3404,
        "lastSeen": 1719769963137,
        "authStatus": 0,
        "guest": false,
        "active": true,
        "manager": false,
        "downPacket": 240,
        "upPacket": 2534
      },
      {
        "mac": "98-25-4A-5F-34-AE",
        "name": "Luz Cocina Galeron",
        "hostName": "L530",
        "deviceType": "unknown",
        "ip": "192.168.10.108",
        "ipv6List": [],
        "connectType": 1,
        "connectDevType": "ap",
        "connectedToWirelessRouter": false,
        "wireless": true,
        "ssid": "GalCaf",
        "signalLevel": 80,
        "healthScore": -1,
        "signalRank": 4,
        "wifiMode": 4,
        "apName": "Galeron AP",
        "apMac": "98-25-4A-41-5D-C2",
        "radioId": 0,
        "channel": 6,
        "rxRate": 54000,
        "txRate": 72222,
        "powerSave": false,
        "rssi": -58,
        "snr": 37,
        "vid": 0,
        "dot1xIdentity": "",
        "activity": 232,
        "trafficDown": 460548,
        "trafficUp": 5005114,
        "uptime": 21824,
        "lastSeen": 1719770002776,
        "authStatus": 0,
        "guest": false,
        "active": true,
        "manager": false,
        "downPacket": 3264,
        "upPacket": 17187,
        "support5g2": false,
        "multiLink": []
      },
      {
        "mac": "74-FE-CE-FA-BD-53",
        "name": "Enchufe Camaras Cabaña",
        "hostName": "P105",
        "deviceType": "unknown",
        "ip": "192.168.10.107",
        "ipv6List": [],
        "connectType": 1,
        "connectDevType": "ap",
        "connectedToWirelessRouter": false,
        "wireless": true,
        "ssid": "Del Rio",
        "signalLevel": 65,
        "healthScore": -1,
        "signalRank": 4,
        "wifiMode": 4,
        "apName": "Cabaña AP",
        "apMac": "40-ED-00-47-81-92",
        "radioId": 0,
        "channel": 1,
        "rxRate": 72109,
        "txRate": 72222,
        "powerSave": false,
        "rssi": -64,
        "snr": 31,
        "vid": 0,
        "dot1xIdentity": "",
        "activity": 0,
        "trafficDown": 1034781,
        "trafficUp": 14754141,
        "uptime": 96917,
        "lastSeen": 1719769998308,
        "authStatus": 0,
        "guest": false,
        "active": true,
        "manager": false,
        "downPacket": 5554,
        "upPacket": 33438,
        "support5g2": false,
        "multiLink": []
      },
      {
        "mac": "98-25-4A-5F-45-1A",
        "name": "Luz Cocina Cabaña",
        "hostName": "L530",
        "deviceType": "unknown",
        "ip": "192.168.10.111",
        "ipv6List": [],
        "connectType": 1,
        "connectDevType": "ap",
        "connectedToWirelessRouter": false,
        "wireless": true,
        "ssid": "Del Rio",
        "signalLevel": 67,
        "healthScore": -1,
        "signalRank": 4,
        "wifiMode": 4,
        "apName": "Cabaña AP",
        "apMac": "40-ED-00-47-81-92",
        "radioId": 0,
        "channel": 1,
        "rxRate": 54000,
        "txRate": 72222,
        "powerSave": false,
        "rssi": -63,
        "snr": 32,
        "vid": 0,
        "dot1xIdentity": "",
        "activity": 0,
        "trafficDown": 608220,
        "trafficUp": 12912480,
        "uptime": 78297,
        "lastSeen": 1719769998308,
        "authStatus": 0,
        "guest": false,
        "active": true,
        "manager": false,
        "downPacket": 5533,
        "upPacket": 39993,
        "support5g2": false,
        "multiLink": []
      },
      {
        "mac": "A8-42-A1-1D-6A-BC",
        "name": "Luz Afuera Cabaña (Este)",
        "hostName": "L510",
        "deviceType": "unknown",
        "ip": "192.168.10.109",
        "ipv6List": [],
        "connectType": 1,
        "connectDevType": "ap",
        "connectedToWirelessRouter": false,
        "wireless": true,
        "ssid": "Del Rio",
        "signalLevel": 65,
        "healthScore": -1,
        "signalRank": 4,
        "wifiMode": 4,
        "apName": "Cabaña AP",
        "apMac": "40-ED-00-47-81-92",
        "radioId": 0,
        "channel": 1,
        "rxRate": 72109,
        "txRate": 72222,
        "powerSave": false,
        "rssi": -64,
        "snr": 31,
        "vid": 0,
        "dot1xIdentity": "",
        "activity": 0,
        "trafficDown": 484655,
        "trafficUp": 11913414,
        "uptime": 78307,
        "lastSeen": 1719769998308,
        "authStatus": 0,
        "guest": false,
        "active": true,
        "manager": false,
        "downPacket": 3187,
        "upPacket": 34824,
        "support5g2": false,
        "multiLink": []
      },
      {
        "mac": "5C-E9-1E-81-B2-68",
        "name": "Hectors-MBPMax",
        "hostName": "Hectors-MBPMax",
        "deviceType": "notebook",
        "ip": "192.168.10.20",
        "ipv6List": [
          "fe80::1830:7589:3476:4138"
        ],
        "connectType": 1,
        "connectDevType": "ap",
        "connectedToWirelessRouter": false,
        "wireless": true,
        "ssid": "Del Rio",
        "signalLevel": 60,
        "healthScore": -1,
        "signalRank": 3,
        "wifiMode": 5,
        "apName": "Galeron AP",
        "apMac": "98-25-4A-41-5D-C2",
        "radioId": 1,
        "channel": 36,
        "rxRate": 585000,
        "txRate": 650000,
        "powerSave": false,
        "rssi": -66,
        "snr": 29,
        "vid": 0,
        "dot1xIdentity": "",
        "activity": 8007,
        "trafficDown": 538987430,
        "trafficUp": 94818859,
        "uptime": 6894,
        "lastSeen": 1719770002776,
        "authStatus": 0,
        "guest": false,
        "active": true,
        "manager": false,
        "downPacket": 650990,
        "upPacket": 485586,
        "support5g2": false,
        "multiLink": []
      },
      {
        "mac": "A8-42-A1-1D-6B-00",
        "name": "Luz Terraza Galeron (Este)",
        "hostName": "L510",
        "deviceType": "unknown",
        "ip": "192.168.10.106",
        "ipv6List": [],
        "connectType": 1,
        "connectDevType": "ap",
        "connectedToWirelessRouter": false,
        "wireless": true,
        "ssid": "Del Rio",
        "signalLevel": 12,
        "healthScore": -1,
        "signalRank": 1,
        "wifiMode": 4,
        "apName": "Cabaña AP",
        "apMac": "40-ED-00-47-81-92",
        "radioId": 0,
        "channel": 1,
        "rxRate": 13000,
        "txRate": 11000,
        "powerSave": false,
        "rssi": -85,
        "snr": 10,
        "vid": 0,
        "dot1xIdentity": "",
        "activity": 0,
        "trafficDown": 440990,
        "trafficUp": 4364777,
        "uptime": 21837,
        "lastSeen": 1719769998308,
        "authStatus": 0,
        "guest": false,
        "active": true,
        "manager": false,
        "downPacket": 2370,
        "upPacket": 11854,
        "support5g2": false,
        "multiLink": []
      },
      {
        "mac": "BC-51-FE-CA-7C-46",
        "name": "Camaras Cabaña",
        "hostName": "camarasloterio",
        "deviceType": "unknown",
        "ip": "192.168.10.13",
        "connectType": 2,
        "connectDevType": "gateway",
        "connectedToWirelessRouter": false,
        "wireless": false,
        "healthScore": -1,
        "gatewayMac": "98-25-4A-63-B5-1E",
        "gatewayName": "Gateway",
        "vid": 1,
        "networkName": "Default LAN",
        "activity": 160,
        "trafficDown": 205442,
        "trafficUp": 210123,
        "uptime": 51143,
        "lastSeen": 1719769963137,
        "authStatus": 0,
        "guest": false,
        "active": true,
        "manager": false,
        "downPacket": 624,
        "upPacket": 2668
      },
      {
        "mac": "74-FE-CE-FC-64-AC",
        "name": "Hub Galeron",
        "hostName": "H100",
        "deviceType": "unknown",
        "ip": "192.168.10.103",
        "ipv6List": [],
        "connectType": 1,
        "connectDevType": "ap",
        "connectedToWirelessRouter": false,
        "wireless": true,
        "ssid": "Del Rio",
        "signalLevel": 100,
        "healthScore": -1,
        "signalRank": 5,
        "wifiMode": 4,
        "apName": "Galeron AP",
        "apMac": "98-25-4A-41-5D-C2",
        "radioId": 0,
        "channel": 6,
        "rxRate": 72109,
        "txRate": 72222,
        "powerSave": false,
        "rssi": -44,
        "snr": 51,
        "vid": 0,
        "dot1xIdentity": "",
        "activity": 464,
        "trafficDown": 13108825,
        "trafficUp": 5754706,
        "uptime": 17944,
        "lastSeen": 1719770002776,
        "authStatus": 0,
        "guest": false,
        "active": true,
        "manager": false,
        "downPacket": 36637,
        "upPacket": 18500,
        "support5g2": false,
        "multiLink": []
      },
      {
        "mac": "98-25-4A-F9-27-B2",
        "name": "Camara Patio Cabaña",
        "hostName": "C510W",
        "deviceType": "unknown",
        "ip": "192.168.10.18",
        "ipv6List": [],
        "connectType": 1,
        "connectDevType": "ap",
        "connectedToWirelessRouter": false,
        "wireless": true,
        "ssid": "Del Rio",
        "signalLevel": 100,
        "healthScore": -1,
        "signalRank": 5,
        "wifiMode": 4,
        "apName": "Cabaña AP",
        "apMac": "40-ED-00-47-81-92",
        "radioId": 0,
        "channel": 1,
        "rxRate": 72109,
        "txRate": 72222,
        "powerSave": false,
        "rssi": -40,
        "snr": 55,
        "vid": 0,
        "dot1xIdentity": "",
        "activity": 1288,
        "trafficDown": 18799289,
        "trafficUp": 269028575,
        "uptime": 78287,
        "lastSeen": 1719769998308,
        "authStatus": 0,
        "guest": false,
        "active": true,
        "manager": false,
        "downPacket": 286060,
        "upPacket": 406889,
        "support5g2": false,
        "multiLink": []
      },
      {
        "mac": "74-FE-CE-FA-A4-BE",
        "name": "Enchufe Musica Galeron",
        "hostName": "P105",
        "deviceType": "unknown",
        "ip": "192.168.10.15",
        "ipv6List": [],
        "connectType": 1,
        "connectDevType": "ap",
        "connectedToWirelessRouter": false,
        "wireless": true,
        "ssid": "GalCaf",
        "signalLevel": 92,
        "healthScore": -1,
        "signalRank": 5,
        "wifiMode": 4,
        "apName": "Galeron AP",
        "apMac": "98-25-4A-41-5D-C2",
        "radioId": 0,
        "channel": 6,
        "rxRate": 72109,
        "txRate": 72222,
        "powerSave": false,
        "rssi": -53,
        "snr": 42,
        "vid": 0,
        "dot1xIdentity": "",
        "activity": 463,
        "trafficDown": 918777,
        "trafficUp": 4760303,
        "uptime": 21824,
        "lastSeen": 1719770002776,
        "authStatus": 0,
        "guest": false,
        "active": true,
        "manager": false,
        "downPacket": 4781,
        "upPacket": 11917,
        "support5g2": false,
        "multiLink": []
      },
      {
        "mac": "00-22-6C-34-19-6F",
        "name": "Parlantes Cabaña",
        "hostName": "S50",
        "deviceType": "unknown",
        "ip": "192.168.10.17",
        "ipv6List": [
          "fe80::222:6cff:fe34:196f"
        ],
        "connectType": 1,
        "connectDevType": "ap",
        "connectedToWirelessRouter": false,
        "wireless": true,
        "ssid": "Del Rio",
        "signalLevel": 90,
        "healthScore": -1,
        "signalRank": 5,
        "wifiMode": 4,
        "apName": "Cabaña AP",
        "apMac": "40-ED-00-47-81-92",
        "radioId": 0,
        "channel": 1,
        "rxRate": 72109,
        "txRate": 72222,
        "powerSave": false,
        "rssi": -54,
        "snr": 41,
        "vid": 0,
        "dot1xIdentity": "",
        "activity": 7312,
        "trafficDown": 14555843,
        "trafficUp": 1318012,
        "uptime": 1937,
        "lastSeen": 1719769998308,
        "authStatus": 0,
        "guest": false,
        "active": true,
        "manager": false,
        "downPacket": 13362,
        "upPacket": 12921,
        "support5g2": false,
        "multiLink": []
      },
      {
        "mac": "74-FE-CE-FA-BD-8F",
        "name": "Enchufe Musica Cabaña",
        "hostName": "P105",
        "deviceType": "unknown",
        "ip": "192.168.10.16",
        "ipv6List": [],
        "connectType": 1,
        "connectDevType": "ap",
        "connectedToWirelessRouter": false,
        "wireless": true,
        "ssid": "Del Rio",
        "signalLevel": 77,
        "healthScore": -1,
        "signalRank": 4,
        "wifiMode": 4,
        "apName": "Cabaña AP",
        "apMac": "40-ED-00-47-81-92",
        "radioId": 0,
        "channel": 1,
        "rxRate": 72109,
        "txRate": 72222,
        "powerSave": false,
        "rssi": -59,
        "snr": 36,
        "vid": 0,
        "dot1xIdentity": "",
        "activity": 0,
        "trafficDown": 1117658,
        "trafficUp": 11853397,
        "uptime": 78307,
        "lastSeen": 1719769998308,
        "authStatus": 0,
        "guest": false,
        "active": true,
        "manager": false,
        "downPacket": 5982,
        "upPacket": 28739,
        "support5g2": false,
        "multiLink": []
      },
      {
        "mac": "E4-FA-C4-A7-47-6A",
        "name": "Hub Cabaña",
        "hostName": "H100",
        "deviceType": "unknown",
        "ip": "192.168.10.110",
        "ipv6List": [],
        "connectType": 1,
        "connectDevType": "ap",
        "connectedToWirelessRouter": false,
        "wireless": true,
        "ssid": "Del Rio",
        "signalLevel": 70,
        "healthScore": -1,
        "signalRank": 4,
        "wifiMode": 4,
        "apName": "Cabaña AP",
        "apMac": "40-ED-00-47-81-92",
        "radioId": 0,
        "channel": 1,
        "rxRate": 39000,
        "txRate": 72222,
        "powerSave": false,
        "rssi": -62,
        "snr": 33,
        "vid": 0,
        "dot1xIdentity": "",
        "activity": 0,
        "trafficDown": 49108447,
        "trafficUp": 13194905,
        "uptime": 78297,
        "lastSeen": 1719769998308,
        "authStatus": 0,
        "guest": false,
        "active": true,
        "manager": false,
        "downPacket": 125260,
        "upPacket": 47090,
        "support5g2": false,
        "multiLink": []
      },
      {
        "mac": "00-22-6C-66-17-35",
        "name": "Parlantes Galeron",
        "hostName": "Parlantes",
        "deviceType": "unknown",
        "ip": "192.168.10.14",
        "ipv6List": [],
        "connectType": 1,
        "connectDevType": "ap",
        "connectedToWirelessRouter": false,
        "wireless": true,
        "ssid": "GalCaf",
        "signalLevel": 100,
        "healthScore": -1,
        "signalRank": 5,
        "wifiMode": 4,
        "apName": "Galeron AP",
        "apMac": "98-25-4A-41-5D-C2",
        "radioId": 0,
        "channel": 6,
        "rxRate": 72109,
        "txRate": 72222,
        "powerSave": false,
        "rssi": -44,
        "snr": 51,
        "vid": 0,
        "dot1xIdentity": "",
        "activity": 4954,
        "trafficDown": 346260,
        "trafficUp": 54986,
        "uptime": 33,
        "lastSeen": 1719770002776,
        "authStatus": 0,
        "guest": false,
        "active": true,
        "manager": false,
        "downPacket": 309,
        "upPacket": 325,
        "support5g2": false,
        "multiLink": []
      },
      {
        "mac": "98-25-4A-5F-4A-47",
        "name": "Luz Terraza Galeron (Oeste)",
        "hostName": "L530",
        "deviceType": "unknown",
        "ip": "192.168.10.112",
        "ipv6List": [],
        "connectType": 1,
        "connectDevType": "ap",
        "connectedToWirelessRouter": false,
        "wireless": true,
        "ssid": "GalCaf",
        "signalLevel": 5,
        "healthScore": -1,
        "signalRank": 1,
        "wifiMode": 4,
        "apName": "Cabaña AP",
        "apMac": "40-ED-00-47-81-92",
        "radioId": 0,
        "channel": 1,
        "rxRate": 5500,
        "txRate": 11000,
        "powerSave": false,
        "rssi": -88,
        "snr": 7,
        "vid": 0,
        "dot1xIdentity": "",
        "activity": 0,
        "trafficDown": 500497,
        "trafficUp": 5354102,
        "uptime": 21827,
        "lastSeen": 1719769998308,
        "authStatus": 0,
        "guest": false,
        "active": true,
        "manager": false,
        "downPacket": 2628,
        "upPacket": 63243,
        "support5g2": false,
        "multiLink": []
      },
      {
        "mac": "74-FE-CE-FA-BE-B6",
        "name": "Enchufe Camaras Galeron",
        "hostName": "P105",
        "deviceType": "unknown",
        "ip": "192.168.10.104",
        "ipv6List": [],
        "connectType": 1,
        "connectDevType": "ap",
        "connectedToWirelessRouter": false,
        "wireless": true,
        "ssid": "GalCaf",
        "signalLevel": 72,
        "healthScore": -1,
        "signalRank": 4,
        "wifiMode": 4,
        "apName": "Galeron AP",
        "apMac": "98-25-4A-41-5D-C2",
        "radioId": 0,
        "channel": 6,
        "rxRate": 72109,
        "txRate": 72222,
        "powerSave": false,
        "rssi": -61,
        "snr": 34,
        "vid": 0,
        "dot1xIdentity": "",
        "activity": 464,
        "trafficDown": 841822,
        "trafficUp": 4806003,
        "uptime": 21814,
        "lastSeen": 1719770002776,
        "authStatus": 0,
        "guest": false,
        "active": true,
        "manager": false,
        "downPacket": 4345,
        "upPacket": 11500,
        "support5g2": false,
        "multiLink": []
      },
      {
        "mac": "00-E0-4C-36-C7-ED",
        "name": "Omada Controller (LAN)",
        "hostName": "delrio-controller",
        "deviceType": "unknown",
        "ip": "192.168.10.10",
        "connectType": 2,
        "connectDevType": "gateway",
        "connectedToWirelessRouter": false,
        "wireless": false,
        "healthScore": -1,
        "gatewayMac": "98-25-4A-63-B5-1E",
        "gatewayName": "Gateway",
        "vid": 1,
        "networkName": "Default LAN",
        "activity": 894,
        "trafficDown": 467130,
        "trafficUp": 4109473,
        "uptime": 567173,
        "lastSeen": 1719769963137,
        "authStatus": 0,
        "guest": false,
        "active": true,
        "manager": true,
        "downPacket": 2607,
        "upPacket": 6387
      }
    ],
    "clientStat": {
      "total": 19,
      "wireless": 16,
      "wired": 3,
      "num2g": 14,
      "num5g": 2,
      "num6g": 0,
      "numUser": 19,
      "numGuest": 0,
      "numWirelessUser": 16,
      "numWirelessGuest": 0,
      "num2gUser": 14,
      "num5gUser": 2,
      "num6gUser": 0,
      "num2gGuest": 0,
      "num5gGuest": 0,
      "num6gGuest": 0,
      "poor": 0,
      "fair": 0,
      "noData": 19,
      "good": 0
    }
  }
}